njhowell_busylight/Auth.py
njhowell_busylight/BusyLightAPI.py
njhowell_busylight/Light.py
njhowell_busylight/__init__.py
njhowell_busylight-0.0.7.dist-info/LICENSE
njhowell_busylight-0.0.7.dist-info/METADATA
njhowell_busylight-0.0.7.dist-info/WHEEL
njhowell_busylight-0.0.7.dist-info/top_level.txt
njhowell_busylight-0.0.7.dist-info/RECORD
